examples/create_synthetic_data.py
examples/create_synthetic_data2.py
examples/dft_workflow.py
examples/generate_curve_test_cases.py
examples/novelty_assesment_microscopy.py
examples/novelty_assesment_spectroscopy.py
examples/run_curve_agent_test.py
examples/synthetic_data_gen.py
examples/test_hyperspectral_agent.py
examples/test_hyperspectral_agent2.py
examples/test_hyperspectral_agent3.py
examples/curve_run_output/custom_processing_fail/preprocessing/custom_preprocessing_script_1d.py
examples/curve_run_output/custom_processing_success/preprocessing/custom_preprocessing_script_1d.py
scilink/__init__.py
scilink/auth.py
scilink/executors.py
scilink/__pycache__/__init__.cpython-311.pyc
scilink/__pycache__/auth.cpython-311.pyc
scilink/__pycache__/executors.cpython-311.pyc
scilink/agents/__init__.py
scilink/agents/__pycache__/__init__.cpython-311.pyc
scilink/agents/exp_agents/__init__.py
scilink/agents/exp_agents/atomistic_microscopy_agent.py
scilink/agents/exp_agents/base_agent.py
scilink/agents/exp_agents/curve_fitting_agent.py
scilink/agents/exp_agents/holistic_microscopy_agent.py
scilink/agents/exp_agents/human_feedback.py
scilink/agents/exp_agents/hyperspectral_analysis_agent.py
scilink/agents/exp_agents/instruct.py
scilink/agents/exp_agents/metadata_converter.py
scilink/agents/exp_agents/microscopy_agent.py
scilink/agents/exp_agents/orchestrator_agent.py
scilink/agents/exp_agents/preprocess.py
scilink/agents/exp_agents/recommendation_agent.py
scilink/agents/exp_agents/sam_microscopy_agent.py
scilink/agents/exp_agents/utils.py
scilink/agents/exp_agents/__pycache__/__init__.cpython-311.pyc
scilink/agents/exp_agents/__pycache__/atomistic_microscopy_agent.cpython-311.pyc
scilink/agents/exp_agents/__pycache__/base_agent.cpython-311.pyc
scilink/agents/exp_agents/__pycache__/curve_fitting_agent.cpython-311.pyc
scilink/agents/exp_agents/__pycache__/holistic_microscopy_agent.cpython-311.pyc
scilink/agents/exp_agents/__pycache__/human_feedback.cpython-311.pyc
scilink-0.0.7.dist-info/METADATA
scilink-0.0.7.dist-info/WHEEL
scilink-0.0.7.dist-info/entry_points.txt
scilink-0.0.7.dist-info/top_level.txt
scilink-0.0.7.dist-info/RECORD
