Metadata-Version: 2.4
Name: scilink
Version: 0.0.7
Summary: A framework for bridging experimental observations with literature analysis and computational materials modeling via large language models
Author-email: SciLink Team <maxim.ziatdinov@gmail.com>
Project-URL: Homepage, https://github.com/scilinkllm/scilink
Project-URL: Bug Tracker, https://github.com/scilink/scilink/issues
Keywords: materials science,computational modeling,machine learning,large language models,generative AI,microscopy,spectroscopy,density functional theory,atomic simulation,experimental analysis,literature mining
Classifier: Development Status :: 4 - Beta
Classifier: Intended Audience :: Science/Research
Classifier: Topic :: Scientific/Engineering :: Physics
Classifier: Topic :: Scientific/Engineering :: Chemistry
Classifier: Topic :: Scientific/Engineering :: Artificial Intelligence
Classifier: License :: OSI Approved :: MIT License
Classifier: Programming Language :: Python :: 3
Classifier: Programming Language :: Python :: 3.11
Classifier: Programming Language :: Python :: 3.12
Classifier: Operating System :: OS Independent
Requires-Python: >=3.11
Requires-Dist: google-generativeai>=0.8.5
Requires-Dist: atomai>=0.8.1
Requires-Dist: edison-client>=0.7.6
Requires-Dist: ase>=0.8.5
Requires-Dist: aimsgb>=1.1.1
Requires-Dist: gdown>=5.2.0
Requires-Dist: atomate2>=0.0.21
Requires-Dist: faiss-cpu>=1.12.0
Requires-Dist: mdanalysis>=2.9.0
Requires-Dist: pymupdf>=1.26.5
Requires-Dist: pdfplumber>=0.11.7
